setup.py
inside/__init__.py
inside/isInside.py
inside/parse.py
inside/util.py
inside.egg-info/PKG-INFO
inside.egg-info/SOURCES.txt
inside.egg-info/dependency_links.txt
inside.egg-info/top_level.txt