Metadata-Version: 2.1
Name: inside
Version: 0.0.2
Summary: Collision detection with polygons.
Home-page: https://github.com/Tsangares/overlap
Author: William Wyatt
Author-email: wwyatt@ucsc.edu
License: UNKNOWN
Platform: UNKNOWN
Classifier: Programming Language :: Python :: 3
Classifier: License :: OSI Approved :: MIT License
